korea_investment_stock/__init__.py
korea_investment_stock/config_resolver.py
korea_investment_stock/constants.py
korea_investment_stock/korea_investment_stock.py
korea_investment_stock/test_integration_us_stocks.py
korea_investment_stock/test_korea_investment_stock.py
korea_investment_stock/test_master_cache.py
korea_investment_stock/cache/__init__.py
korea_investment_stock/cache/cache_manager.py
korea_investment_stock/cache/cached_korea_investment.py
korea_investment_stock/cache/test_cache_manager.py
korea_investment_stock/cache/test_cached_integration.py
korea_investment_stock/config/__init__.py
korea_investment_stock/config/config.py
korea_investment_stock/config/test_config.py
korea_investment_stock/config/test_env_auto_detection.py
korea_investment_stock/config/test_hybrid_config.py
korea_investment_stock/ipo/__init__.py
korea_investment_stock/ipo/ipo_api.py
korea_investment_stock/ipo/ipo_helpers.py
korea_investment_stock/parsers/__init__.py
korea_investment_stock/parsers/master_parser.py
korea_investment_stock/parsers/overseas_master_parser.py
korea_investment_stock/parsers/test_overseas_master_parser.py
korea_investment_stock/rate_limit/__init__.py
korea_investment_stock/rate_limit/rate_limited_korea_investment.py
korea_investment_stock/rate_limit/rate_limiter.py
korea_investment_stock/rate_limit/test_rate_limited_integration.py
korea_investment_stock/rate_limit/test_rate_limiter.py
korea_investment_stock/tests/__init__.py
korea_investment_stock/tests/conftest.py
korea_investment_stock/tests/test_integration_investor.py
korea_investment_stock/tests/test_investor_trading.py
korea_investment_stock/tests/test_investor_trend_by_market.py
korea_investment_stock/tests/test_overseas_symbols_integration.py
korea_investment_stock/tests/test_redis_integration.py
korea_investment_stock/tests/test_token_refresh.py
korea_investment_stock/token/__init__.py
korea_investment_stock/token/factory.py
korea_investment_stock/token/manager.py
korea_investment_stock-0.16.1.dist-info/licenses/LICENSE
korea_investment_stock-0.16.1.dist-info/METADATA
korea_investment_stock-0.16.1.dist-info/WHEEL
korea_investment_stock-0.16.1.dist-info/top_level.txt
korea_investment_stock-0.16.1.dist-info/RECORD
