Metadata-Version: 2.4
Name: korea-investment-stock
Version: 0.16.1
Summary: Pure Python wrapper for Korea Investment Securities OpenAPI
Author-email: Jonghun Yoo <jonghun.yoo@pyquant.co.kr>, Brayden Jo <brayden.jo@pyquant.co.kr>, Frank Oh <kenshin579@gmail.com>
License: MIT
Project-URL: Github, https://github.com/kenshin579/korea-investment-stock
Project-URL: Bug Tracker, https://github.com/kenshin579/korea-investment-stock/issues
Requires-Python: >=3.11
License-File: LICENSE
Requires-Dist: requests
Requires-Dist: pandas
Requires-Dist: pyyaml>=6.0
Provides-Extra: redis
Requires-Dist: redis>=4.5.0; extra == "redis"
Provides-Extra: dev
Requires-Dist: pytest>=7.0.0; extra == "dev"
Requires-Dist: pytest-mock>=3.10.0; extra == "dev"
Requires-Dist: pytest-cov>=4.0.0; extra == "dev"
Requires-Dist: fakeredis>=2.10.0; extra == "dev"
Requires-Dist: testcontainers>=4.0.0; extra == "dev"
Dynamic: license-file
